django_mcpx-0.1.2.dist-info/licenses/LICENSE
mcpx/__init__.py
mcpx/auth.py
mcpx/management/__init__.py
mcpx/management/commands/__init__.py
mcpx/management/commands/runmcp.py
django_mcpx-0.1.2.dist-info/METADATA
django_mcpx-0.1.2.dist-info/WHEEL
django_mcpx-0.1.2.dist-info/top_level.txt
django_mcpx-0.1.2.dist-info/RECORD
